MANIFEST.in
README.md
config.yaml
setup.cfg
setup.py
examples/gamma_surface.py
examples/pbe_bandstructure.py
examples/thermodynamic_stability.py
twod_materials/__init__.py
twod_materials/config.yaml
twod_materials/potcar_symbols.yaml
twod_materials/test_utils.py
twod_materials/utils.py
twod_materials.egg-info/PKG-INFO
twod_materials.egg-info/SOURCES.txt
twod_materials.egg-info/dependency_links.txt
twod_materials.egg-info/requires.txt
twod_materials.egg-info/top_level.txt
twod_materials/electronic_structure/__init__.py
twod_materials/electronic_structure/analysis.py
twod_materials/electronic_structure/startup.py
twod_materials/electronic_structure/tests/test_electronic_structure.py
twod_materials/friction/__init__.py
twod_materials/friction/analysis.py
twod_materials/friction/startup.py
twod_materials/friction/tests/test_friction.py
twod_materials/intercalation/__init__.py
twod_materials/intercalation/analysis.py
twod_materials/intercalation/startup.py
twod_materials/intercalation/tests/test_intercalation.py
twod_materials/magnetism/__init__.py
twod_materials/magnetism/analysis.py
twod_materials/magnetism/startup.py
twod_materials/pourbaix/__init__.py
twod_materials/pourbaix/analysis.py
twod_materials/pourbaix/end_members.yaml
twod_materials/pourbaix/ion_colors.yaml
twod_materials/pourbaix/ions.yaml
twod_materials/pourbaix/startup.py
twod_materials/stability/__init__.py
twod_materials/stability/analysis.py
twod_materials/stability/startup.py
twod_materials/stability/tests/test_stability.py