Metadata-Version: 1.1
Name: twod-materials
Version: 0.0.4
Summary: High throughput 2D material modules
Home-page: https://github.com/ashtonmv/twod_materials
Author: Michael Ashton
Author-email: mashton@ufl.edu
License: GNU
Download-URL: https://github.com/ashtonmv/twod_materials/tarball/0.0.4
Platform: UNKNOWN
